mdfind/__init__.py
mdfind/_api.py
mdfind/py.typed
mdfind_wrapper-0.1.5.dist-info/LICENSE
mdfind_wrapper-0.1.5.dist-info/METADATA
mdfind_wrapper-0.1.5.dist-info/WHEEL
mdfind_wrapper-0.1.5.dist-info/top_level.txt
mdfind_wrapper-0.1.5.dist-info/RECORD
