Metadata-Version: 2.1
Name: mdfind-wrapper
Version: 0.1.5
Summary: A python library that wraps the mdfind.
Home-page: https://github.com/dmkskn/mdfind-wrapper
Author: Dima Koskin
Author-email: dmksknn@gmail.com
License: Unlicense
Keywords: macos,mdfind,spotlight
Platform: UNKNOWN
Classifier: Programming Language :: Python :: 3.6
Classifier: Programming Language :: Python :: 3 :: Only
Classifier: Operating System :: MacOS
Requires-Python: >=3.6
